COPYING
MANIFEST.in
README.rst
setup.py
sixelterm/__init__.py
sixelterm/scanner.py
sixelterm/sixelterm.py
sixelterm.egg-info/PKG-INFO
sixelterm.egg-info/SOURCES.txt
sixelterm.egg-info/dependency_links.txt
sixelterm.egg-info/eager_resources.txt
sixelterm.egg-info/entry_points.txt
sixelterm.egg-info/requires.txt
sixelterm.egg-info/top_level.txt
sixelterm.egg-info/zip-safe