Metadata-Version: 1.1
Name: sixelterm
Version: 0.0.10
Summary: Display JPEG/PNG image with cat command, on some terminals support SIXEL (RLogin/mlterm/tanasinn). Inspired by GateOne.
Home-page: https://github.com/saitoha/sixelterm
Author: Hayaki Saito (user@zuse.jp)
Author-email: user@zuse.jp
License: GPL v3
Keywords: sixel terminal
Platform: UNKNOWN
Classifier: Development Status :: 4 - Beta
Classifier: Topic :: Terminals
Classifier: Environment :: Console
Classifier: Intended Audience :: End Users/Desktop
Classifier: License :: OSI Approved :: GNU General Public License (GPL)
Classifier: Programming Language :: Python
